Packages/__init__.py
Packages/my_module.py
Tests/Test_mymodule.py
Tests/__init__.py
DenemeG-0.1.2.dist-info/LICENSE
DenemeG-0.1.2.dist-info/METADATA
DenemeG-0.1.2.dist-info/WHEEL
DenemeG-0.1.2.dist-info/top_level.txt
DenemeG-0.1.2.dist-info/RECORD
