Metadata-Version: 2.1
Name: DenemeG
Version: 0.1.2
Summary: A simple package to greet users
Home-page: https://github.com/GoktugSuvorun/DenemeG.git
Author: Göktuğ
Author-email: goktugonal76@gmail.com
Classifier: Programming Language :: Python :: 3
Classifier: License :: OSI Approved :: MIT License
Classifier: Operating System :: OS Independent
Requires-Python: >=3.6
License-File: LICENSE
Requires-Dist: numpy
Requires-Dist: pandas
